{"val_loss": 0.5632528573274612, "val_accuracy": 0.8152436017990112, "done": true, "timesteps_total": null, "episodes_total": null, "training_iteration": 1, "experiment_id": "a5a4cf312f384b9782a2e849c0910617", "date": "2021-07-12_16-02-34", "timestamp": 1626105754, "time_this_iter_s": 37.753905057907104, "time_total_s": 37.753905057907104, "pid": 240, "hostname": "16de683cbd00", "node_ip": "172.17.0.3", "config": {"window_size": 100.0, "step_size": 0.9, "kernel_size": 8.0, "pool_size": 2.0, "optimizer": "adam", "activation": "relu", "learning_rate": 0.0013411576915910556, "temporal_filters": 20.0, "batch_normalization": true, "n_conv_layers": 0.0, "n_fc_layers": 2.0, "n_neurons_2nd_layer": 0.55, "dropout_rate": 0}, "time_since_restore": 37.753905057907104, "timesteps_since_restore": 0, "iterations_since_restore": 1, "trial_id": "2655908a"}
