{"val_loss": 1.4091126084327699, "val_accuracy": 0.633152163028717, "done": true, "timesteps_total": null, "episodes_total": null, "training_iteration": 1, "experiment_id": "bc00e38d72c34c619058ac739d244042", "date": "2021-07-13_00-18-17", "timestamp": 1626135497, "time_this_iter_s": 129.45362162590027, "time_total_s": 129.45362162590027, "pid": 138829, "hostname": "4b21eb5d908c", "node_ip": "172.17.0.8", "config": {"window_size": 50.0, "step_size": 0.4, "kernel_size": 8.0, "pool_size": 3.0, "optimizer": "adam", "activation": "relu", "learning_rate": 0.0007543040113470901, "temporal_filters": 40.0, "batch_normalization": false, "n_conv_layers": 1.0, "n_fc_layers": 0.0, "n_neurons_2nd_layer": 0.75, "dropout_rate": 0.6}, "time_since_restore": 129.45362162590027, "timesteps_since_restore": 0, "iterations_since_restore": 1, "trial_id": "157c2662"}
