{"val_loss": 0.6265941381454467, "val_accuracy": 0.6341269910335541, "done": true, "timesteps_total": null, "episodes_total": null, "training_iteration": 1, "experiment_id": "fb50b3305e2e4a04a094a57116f7a940", "date": "2021-07-27_13-00-10", "timestamp": 1627390810, "time_this_iter_s": 22.62277102470398, "time_total_s": 22.62277102470398, "pid": 166072, "hostname": "0ac92cac021f", "node_ip": "172.17.0.2", "config": {"window_size": 50.0, "step_size": 0.7000000000000001, "kernel_size": 8.0, "pool_size": 2.0, "optimizer": "adam", "activation": "relu", "learning_rate": 0.00019420801471479557, "temporal_filters": 50.0, "batch_normalization": false, "n_conv_layers": 1.0, "n_fc_layers": 1.0, "n_neurons_2nd_layer": 0.25, "dropout_rate": 0.6}, "time_since_restore": 22.62277102470398, "timesteps_since_restore": 0, "iterations_since_restore": 1, "trial_id": "704b25fe"}
