{"val_loss": 0.42127281725406646, "val_accuracy": 0.8632734000682831, "done": true, "timesteps_total": null, "episodes_total": null, "training_iteration": 1, "experiment_id": "17697fcc4a1248a5bb171771ed6cf2ad", "date": "2021-07-12_16-19-09", "timestamp": 1626106749, "time_this_iter_s": 23.702759742736816, "time_total_s": 23.702759742736816, "pid": 187, "hostname": "038a6a57d6e8", "node_ip": "172.17.0.6", "config": {"window_size": 100.0, "step_size": 1.0, "kernel_size": 4.0, "pool_size": 3.0, "optimizer": "sgd", "activation": "elu", "learning_rate": 0.005244894846183088, "temporal_filters": 40.0, "batch_normalization": true, "n_conv_layers": 0.0, "n_fc_layers": 0.0, "n_neurons_2nd_layer": 0.45, "dropout_rate": 0.6}, "time_since_restore": 23.702759742736816, "timesteps_since_restore": 0, "iterations_since_restore": 1, "trial_id": "b0d440e2"}
