{"val_loss": 0.34885706305503844, "val_accuracy": 0.8870990753173829, "done": true, "timesteps_total": null, "episodes_total": null, "training_iteration": 1, "experiment_id": "a4e96b29c5be4d1987054673a7d0f93e", "date": "2021-07-04_09-15-15", "timestamp": 1625390115, "time_this_iter_s": 446.9203100204468, "time_total_s": 446.9203100204468, "pid": 165896, "hostname": "2981f4dce3ab", "node_ip": "172.17.0.3", "config": {"window_size": 100.0, "step_size": 0.1, "kernel_size": 2.0, "pool_size": 2.0, "optimizer": "adam", "activation": "elu", "learning_rate": 0.0021221992611783255, "temporal_filters": 40.0, "batch_normalization": false, "n_conv_layers": 0.0, "n_fc_layers": 0.0, "n_neurons_2nd_layer": 0.55, "dropout_rate": 0.6}, "time_since_restore": 446.9203100204468, "timesteps_since_restore": 0, "iterations_since_restore": 1, "trial_id": "0038f060"}
