{"val_loss": 0.6162927031517029, "val_accuracy": 0.6886755406856537, "done": true, "timesteps_total": null, "episodes_total": null, "training_iteration": 1, "experiment_id": "a696d06c02f94a54ade6fe317f7715ff", "date": "2021-07-12_19-39-04", "timestamp": 1626118744, "time_this_iter_s": 76.9416229724884, "time_total_s": 76.9416229724884, "pid": 138440, "hostname": "9d3501cbbd1a", "node_ip": "172.17.0.4", "config": {"window_size": 50.0, "step_size": 0.4, "kernel_size": 2.0, "pool_size": 3.0, "optimizer": "adam", "activation": "elu", "learning_rate": 0.0003899008662624812, "temporal_filters": 50.0, "batch_normalization": true, "n_conv_layers": 0.0, "n_fc_layers": 2.0, "n_neurons_2nd_layer": 0.45, "dropout_rate": 0}, "time_since_restore": 76.9416229724884, "timesteps_since_restore": 0, "iterations_since_restore": 1, "trial_id": "01bede3e"}
