{"val_loss": 0.6937172949314118, "val_accuracy": 0.4946015477180481, "done": true, "timesteps_total": null, "episodes_total": null, "training_iteration": 1, "experiment_id": "e2d98a7032df4fd98d20a857d9a882e6", "date": "2021-07-15_11-04-16", "timestamp": 1626347056, "time_this_iter_s": 66.68674683570862, "time_total_s": 66.68674683570862, "pid": 189879, "hostname": "1c638fbfc758", "node_ip": "172.17.0.3", "config": {"window_size": 100.0, "step_size": 0.4, "kernel_size": 4.0, "pool_size": 3.0, "optimizer": "sgd", "activation": "relu", "learning_rate": 0.00036002335529406745, "temporal_filters": 50.0, "batch_normalization": false, "n_conv_layers": 1.0, "n_fc_layers": 0.0, "n_neurons_2nd_layer": 0.5, "dropout_rate": 0}, "time_since_restore": 66.68674683570862, "timesteps_since_restore": 0, "iterations_since_restore": 1, "trial_id": "d84dc4f0"}
