{"val_loss": 0.515241938829422, "val_accuracy": 0.7355511784553528, "done": true, "timesteps_total": null, "episodes_total": null, "training_iteration": 1, "experiment_id": "45b161b42c964696a16f51e1bace3ebb", "date": "2021-07-13_12-52-51", "timestamp": 1626180771, "time_this_iter_s": 173.40055227279663, "time_total_s": 173.40055227279663, "pid": 106845, "hostname": "1b3816b41068", "node_ip": "172.17.0.3", "config": {"window_size": 50.0, "step_size": 0.9, "kernel_size": 6.0, "pool_size": 3.0, "optimizer": "sgd", "activation": "relu", "learning_rate": 0.0010755541050022528, "temporal_filters": 50.0, "batch_normalization": true, "n_conv_layers": 0.0, "n_fc_layers": 2.0, "n_neurons_2nd_layer": 0.35000000000000003, "dropout_rate": 0}, "time_since_restore": 173.40055227279663, "timesteps_since_restore": 0, "iterations_since_restore": 1, "trial_id": "7419d80e"}
