{"val_loss": 0.44012255072593687, "val_accuracy": 0.7995238125324249, "done": true, "timesteps_total": null, "episodes_total": null, "training_iteration": 1, "experiment_id": "d97b9d6931414cd4aa55c01379ed57ea", "date": "2021-07-27_10-25-58", "timestamp": 1627381558, "time_this_iter_s": 28.41420006752014, "time_total_s": 28.41420006752014, "pid": 42479, "hostname": "f5f37d55ad3d", "node_ip": "172.17.0.5", "config": {"window_size": 100.0, "step_size": 0.2, "kernel_size": 6.0, "pool_size": 3.0, "optimizer": "adam", "activation": "elu", "learning_rate": 6.688139517800643e-05, "temporal_filters": 10.0, "batch_normalization": false, "n_conv_layers": 1.0, "n_fc_layers": 1.0, "n_neurons_2nd_layer": 0.35000000000000003, "dropout_rate": 0.6}, "time_since_restore": 28.41420006752014, "timesteps_since_restore": 0, "iterations_since_restore": 1, "trial_id": "e241e564"}
