{"val_loss": 0.45332291126251223, "val_accuracy": 0.8684884071350097, "done": true, "timesteps_total": null, "episodes_total": null, "training_iteration": 1, "experiment_id": "f0d21fcb119c467f9ad477a4cfa68cad", "date": "2021-07-27_12-33-42", "timestamp": 1627389222, "time_this_iter_s": 28.097277879714966, "time_total_s": 28.097277879714966, "pid": 138319, "hostname": "6f28ddc9333e", "node_ip": "172.17.0.4", "config": {"window_size": 50.0, "step_size": 0.30000000000000004, "kernel_size": 4.0, "pool_size": 2.0, "optimizer": "adam", "activation": "elu", "learning_rate": 0.004850477385735796, "temporal_filters": 20.0, "batch_normalization": false, "n_conv_layers": 1.0, "n_fc_layers": 0.0, "n_neurons_2nd_layer": 0.55, "dropout_rate": 0}, "time_since_restore": 28.097277879714966, "timesteps_since_restore": 0, "iterations_since_restore": 1, "trial_id": "5dd40b1a"}
