{"val_loss": 0.4299909740686417, "val_accuracy": 0.8099066019058228, "done": true, "timesteps_total": null, "episodes_total": null, "training_iteration": 1, "experiment_id": "88929798c63c4e499b901d39e470dee5", "date": "2021-07-14_21-04-51", "timestamp": 1626296691, "time_this_iter_s": 771.9521191120148, "time_total_s": 771.9521191120148, "pid": 57974, "hostname": "1c638fbfc758", "node_ip": "172.17.0.3", "config": {"window_size": 100.0, "step_size": 0.1, "kernel_size": 6.0, "pool_size": 3.0, "optimizer": "adam", "activation": "relu", "learning_rate": 0.00019248292356314995, "temporal_filters": 10.0, "batch_normalization": false, "n_conv_layers": 1.0, "n_fc_layers": 1.0, "n_neurons_2nd_layer": 0.35000000000000003, "dropout_rate": 0}, "time_since_restore": 771.9521191120148, "timesteps_since_restore": 0, "iterations_since_restore": 1, "trial_id": "3b63c2f0"}
