{"val_loss": 0.9211194217205048, "val_accuracy": 0.6572641789913177, "done": true, "timesteps_total": null, "episodes_total": null, "training_iteration": 1, "experiment_id": "d52896da56c34378be2b78aa99a9324f", "date": "2021-07-04_05-02-46", "timestamp": 1625374966, "time_this_iter_s": 84.15737891197205, "time_total_s": 84.15737891197205, "pid": 89658, "hostname": "2ca9eeda055d", "node_ip": "172.17.0.5", "config": {"window_size": 100.0, "step_size": 0.6000000000000001, "kernel_size": 4.0, "pool_size": 2.0, "optimizer": "adam", "activation": "relu", "learning_rate": 0.0075265438060183095, "temporal_filters": 50.0, "batch_normalization": true, "n_conv_layers": 1.0, "n_fc_layers": 0.0, "n_neurons_2nd_layer": 0.65, "dropout_rate": 0}, "time_since_restore": 84.15737891197205, "timesteps_since_restore": 0, "iterations_since_restore": 1, "trial_id": "09fb8226"}
