{"val_loss": 0.6907904326915741, "val_accuracy": 0.5217391431331635, "done": true, "timesteps_total": null, "episodes_total": null, "training_iteration": 1, "experiment_id": "478e30a94e6d4f97a7db062940010fb6", "date": "2021-07-12_20-24-15", "timestamp": 1626121455, "time_this_iter_s": 105.23941278457642, "time_total_s": 105.23941278457642, "pid": 81912, "hostname": "4b21eb5d908c", "node_ip": "172.17.0.8", "config": {"window_size": 50.0, "step_size": 0.30000000000000004, "kernel_size": 6.0, "pool_size": 2.0, "optimizer": "sgd", "activation": "elu", "learning_rate": 0.00025645802920773686, "temporal_filters": 30.0, "batch_normalization": false, "n_conv_layers": 1.0, "n_fc_layers": 0.0, "n_neurons_2nd_layer": 0.6000000000000001, "dropout_rate": 0}, "time_since_restore": 105.23941278457642, "timesteps_since_restore": 0, "iterations_since_restore": 1, "trial_id": "f264ab04"}
