{"val_loss": 0.6465593338012695, "val_accuracy": 0.6407530546188355, "done": true, "timesteps_total": null, "episodes_total": null, "training_iteration": 1, "experiment_id": "dd289aa4337a482ea3460a59eb928a35", "date": "2021-07-27_10-39-57", "timestamp": 1627382397, "time_this_iter_s": 31.523541688919067, "time_total_s": 31.523541688919067, "pid": 193, "hostname": "0ac92cac021f", "node_ip": "172.17.0.2", "config": {"window_size": 50.0, "step_size": 0.6000000000000001, "kernel_size": 2.0, "pool_size": 2.0, "optimizer": "adam", "activation": "relu", "learning_rate": 0.00015800290248539384, "temporal_filters": 30.0, "batch_normalization": true, "n_conv_layers": 1.0, "n_fc_layers": 0.0, "n_neurons_2nd_layer": 0.25, "dropout_rate": 0}, "time_since_restore": 31.523541688919067, "timesteps_since_restore": 0, "iterations_since_restore": 1, "trial_id": "daed90a4"}
