{"val_loss": 0.6723888278007507, "val_accuracy": 0.5914640843868255, "done": true, "timesteps_total": null, "episodes_total": null, "training_iteration": 1, "experiment_id": "9e3c7c018aa349afa2ed7618238ba388", "date": "2021-07-13_08-37-16", "timestamp": 1626165436, "time_this_iter_s": 143.9949827194214, "time_total_s": 143.9949827194214, "pid": 203, "hostname": "f5a588c8d96a", "node_ip": "172.17.0.2", "config": {"window_size": 100.0, "step_size": 0.2, "kernel_size": 2.0, "pool_size": 3.0, "optimizer": "adam", "activation": "elu", "learning_rate": 5.4061461420961345e-05, "temporal_filters": 20.0, "batch_normalization": false, "n_conv_layers": 1.0, "n_fc_layers": 1.0, "n_neurons_2nd_layer": 0.6000000000000001, "dropout_rate": 0}, "time_since_restore": 143.9949827194214, "timesteps_since_restore": 0, "iterations_since_restore": 1, "trial_id": "2ec62078"}
